<?xml version="1.0" encoding="UTF-8"?>
<site pack200="true" digestURL="http://download.eclipse.org/modeling/emf/updates/milestones/" mirrorsURL="http://www.eclipse.org/modeling/download.php?file=/modeling/emf/updates/milestones/site.xml&amp;format=xml">
	<!-- to track downloads, use absolute paths instead: http://www.eclipse.org/downloads/download.php?r=1&amp;file=/modeling/emf/updates/ ... -->

	<description url="http://download.eclipse.org/modeling/emf/updates/milestones/site.xml">
	To install these plugins, point Eclipse at this site. 
	</description>


	<!-- COMPARE 1.1.0M4 S200912150654 (Incubation) -->
	<category-def label="EMF COMPARE SDK (Incubation) 1.1.0M4 S200912150654" name="EMF COMPARE SDK (Incubation) 1.1.0M4 S200912150654">
		<description>
EMF COMPARE SDK (Incubation) 1.1.0M4 S200912150654: contains runtime, source, and documentation.
		</description>
	</category-def>
	<feature id="org.eclipse.emf.compare" version="1.1.0.v200912150654" url="features/org.eclipse.emf.compare_1.1.0.v200912150654.jar" patch="false">
		<category name="EMF COMPARE SDK (Incubation) 1.1.0M4 S200912150654"/>
	</feature>
	<feature id="org.eclipse.emf.compare.ui.capabilities" version="1.1.0.v200912150654" url="features/org.eclipse.emf.compare.ui.capabilities_1.1.0.v200912150654.jar" patch="false">
		<category name="EMF COMPARE SDK (Incubation) 1.1.0M4 S200912150654"/>
	</feature>
	<feature id="org.eclipse.emf.compare.source" version="1.1.0.v200912150654" url="features/org.eclipse.emf.compare.source_1.1.0.v200912150654.jar" patch="false">
		<category name="EMF COMPARE SDK (Incubation) 1.1.0M4 S200912150654"/>
	</feature>
	<feature id="org.eclipse.emf.compare.ui.capabilities.source" version="1.1.0.v200912150654" url="features/org.eclipse.emf.compare.ui.capabilities.source_1.1.0.v200912150654.jar" patch="false">
		<category name="EMF COMPARE SDK (Incubation) 1.1.0M4 S200912150654"/>
	</feature>
	<feature id="org.eclipse.emf.compare.sdk" version="1.1.0.v200912150654" url="features/org.eclipse.emf.compare.sdk_1.1.0.v200912150654.jar" patch="false">
		<category name="EMF COMPARE SDK (Incubation) 1.1.0M4 S200912150654"/>
	</feature>
	<feature id="org.eclipse.emf.compare.doc" version="1.0.1.v200912150654" url="features/org.eclipse.emf.compare.doc_1.0.1.v200912150654.jar" patch="false">
		<category name="EMF COMPARE SDK (Incubation) 1.1.0M4 S200912150654"/>
	</feature>
	<feature id="org.eclipse.emf.compare.team.subversive.source" version="1.1.0.v200912150654" url="features/org.eclipse.emf.compare.team.subversive.source_1.1.0.v200912150654.jar" patch="false">
		<category name="EMF COMPARE SDK (Incubation) 1.1.0M4 S200912150654"/>
	</feature>
	<feature id="org.eclipse.emf.compare.all" version="1.1.0.v200912150654" url="features/org.eclipse.emf.compare.all_1.1.0.v200912150654.jar" patch="false">
		<category name="EMF COMPARE SDK (Incubation) 1.1.0M4 S200912150654"/>
	</feature>
	<feature id="org.eclipse.emf.compare.team.subversive" version="1.1.0.v200912150654" url="features/org.eclipse.emf.compare.team.subversive_1.1.0.v200912150654.jar" patch="false">
		<category name="EMF COMPARE SDK (Incubation) 1.1.0M4 S200912150654"/>
	</feature>

	<!-- COMPARE 1.0.0M3 S200911100435 (Incubation) -->
	<category-def label="EMF COMPARE SDK (Incubation) 1.0.0M3 S200911100435" name="EMF COMPARE SDK (Incubation) 1.0.0M3 S200911100435">
		<description>
EMF COMPARE SDK (Incubation) 1.0.0M3 S200911100435: contains runtime, source, and documentation.
		</description>
	</category-def>
	<feature id="org.eclipse.emf.compare" version="1.0.1.v200911100435" url="features/org.eclipse.emf.compare_1.0.1.v200911100435.jar" patch="false">
		<category name="EMF COMPARE SDK (Incubation) 1.0.0M3 S200911100435"/>
	</feature>
	<feature id="org.eclipse.emf.compare.ui.capabilities" version="1.0.1.v200911100435" url="features/org.eclipse.emf.compare.ui.capabilities_1.0.1.v200911100435.jar" patch="false">
		<category name="EMF COMPARE SDK (Incubation) 1.0.0M3 S200911100435"/>
	</feature>
	<feature id="org.eclipse.emf.compare.source" version="1.0.1.v200911100435" url="features/org.eclipse.emf.compare.source_1.0.1.v200911100435.jar" patch="false">
		<category name="EMF COMPARE SDK (Incubation) 1.0.0M3 S200911100435"/>
	</feature>
	<feature id="org.eclipse.emf.compare.ui.capabilities.source" version="1.0.1.v200911100435" url="features/org.eclipse.emf.compare.ui.capabilities.source_1.0.1.v200911100435.jar" patch="false">
		<category name="EMF COMPARE SDK (Incubation) 1.0.0M3 S200911100435"/>
	</feature>
	<feature id="org.eclipse.emf.compare.sdk" version="1.0.1.v200911100435" url="features/org.eclipse.emf.compare.sdk_1.0.1.v200911100435.jar" patch="false">
		<category name="EMF COMPARE SDK (Incubation) 1.0.0M3 S200911100435"/>
	</feature>
	<feature id="org.eclipse.emf.compare.doc" version="1.0.1.v200911100435" url="features/org.eclipse.emf.compare.doc_1.0.1.v200911100435.jar" patch="false">
		<category name="EMF COMPARE SDK (Incubation) 1.0.0M3 S200911100435"/>
	</feature>
	<feature id="org.eclipse.emf.compare.team.subversive.source" version="1.0.1.v200911100435" url="features/org.eclipse.emf.compare.team.subversive.source_1.0.1.v200911100435.jar" patch="false">
		<category name="EMF COMPARE SDK (Incubation) 1.0.0M3 S200911100435"/>
	</feature>
	<feature id="org.eclipse.emf.compare.all" version="1.0.1.v200911100435" url="features/org.eclipse.emf.compare.all_1.0.1.v200911100435.jar" patch="false">
		<category name="EMF COMPARE SDK (Incubation) 1.0.0M3 S200911100435"/>
	</feature>
	<feature id="org.eclipse.emf.compare.team.subversive" version="1.0.1.v200911100435" url="features/org.eclipse.emf.compare.team.subversive_1.0.1.v200911100435.jar" patch="false">
		<category name="EMF COMPARE SDK (Incubation) 1.0.0M3 S200911100435"/>
	</feature>

</site>
